ytcomment_trends/__init__.py
ytcomment_trends/controllers/google_api/__init__.py
ytcomment_trends/controllers/google_api/auth.py
ytcomment_trends/controllers/google_api/youtube.py
ytcomment_trends/controllers/nlp/__init__.py
ytcomment_trends/controllers/nlp/oseti.py
ytcomment_trends/entrypoint.py
ytcomment_trends/main.py
ytcomment_trends-0.1.7.dist-info/entry_points.txt
ytcomment_trends-0.1.7.dist-info/LICENSE
ytcomment_trends-0.1.7.dist-info/WHEEL
ytcomment_trends-0.1.7.dist-info/METADATA
ytcomment_trends-0.1.7.dist-info/RECORD
