Metadata-Version: 2.1
Name: ytcomment-trends
Version: 0.1.7
Summary: YouTube comment trends analysis tool using oseti
Home-page: https://www.386.jp/works/ytcomment_trends
License: MIT
Author: Kyosuke Miyamura
Author-email: ask@386.jp
Requires-Python: >=3.8,<3.11
Classifier: License :: OSI Approved :: MIT License
Classifier: Programming Language :: Python :: 3
Classifier: Programming Language :: Python :: 3.10
Classifier: Programming Language :: Python :: 3.8
Classifier: Programming Language :: Python :: 3.9
Requires-Dist: google-api-python-client (>=2.36.0,<3.0.0)
Requires-Dist: matplotlib (>=3.5.1,<4.0.0)
Requires-Dist: oseti (>=0.2,<0.3)
Requires-Dist: pandas (>=1.3.5,<2.0.0)
Project-URL: Repository, https://github.com/386jp/ytcomment_trends
